[
  {
    "_id": "rec2KIEuEuc2QUslo",
    "id": "rec2KIEuEuc2QUslo",
    "顯示名稱-華語": "ddio",
    "顯示名稱-en": "ddio",
    "大頭照": "cache/9108f1822c3ca7e0fb4c4ec6df1a0282.jpg",
    "組別": "宣傳組",
    "職稱-華語": "組員",
    "職稱-en": "Member",
    "最後更新時間": "2020-11-30T07:34:08.000Z"
  },
  {
    "_id": "recsPquwHq5uzckEV",
    "id": "recsPquwHq5uzckEV",
    "顯示名稱-華語": "chris",
    "顯示名稱-en": "chris",
    "大頭照": "cache/eeb8aee59b3f531d185e535c3109d974.jpg",
    "組別": "宣傳組",
    "職稱-華語": "組員",
    "職稱-en": "Member",
    "最後更新時間": "2020-11-30T07:34:08.000Z"
  },
  {
    "_id": "recVH4ImD9Zr0aOZa",
    "id": "recVH4ImD9Zr0aOZa",
    "顯示名稱-華語": "游諭 yu",
    "顯示名稱-en": "yu",
    "組別": "宣傳組",
    "職稱-華語": "組員",
    "職稱-en": "Member",
    "最後更新時間": "2020-11-30T07:34:08.000Z"
  },
  {
    "_id": "recm1BPlPcILOihqh",
    "id": "recm1BPlPcILOihqh",
    "顯示名稱-華語": "RR",
    "顯示名稱-en": "delightfullychoatic",
    "組別": "總籌組",
    "職稱-華語": "組員",
    "職稱-en": "Member",
    "最後更新時間": "2020-11-30T07:34:08.000Z"
  },
  {
    "_id": "reckbyEAXjy0Z3Ulx",
    "id": "reckbyEAXjy0Z3Ulx",
    "顯示名稱-華語": "t-monk",
    "顯示名稱-en": "t-monk",
    "大頭照": "cache/c5b01b23c1929560e7c99111c1ef76d0.jpg",
    "組別": "直播組",
    "職稱-華語": "直播導播 P.D.",
    "職稱-en": "P.D.",
    "最後更新時間": "2020-11-30T02:33:17.000Z"
  },
  {
    "_id": "rec8Eb7h2AW4XoM0v",
    "id": "rec8Eb7h2AW4XoM0v",
    "顯示名稱-華語": "Kira",
    "顯示名稱-en": "Kira",
    "大頭照": "cache/59d532a6d0f5ac5aebd20ad2e2dd158d.jpg",
    "組別": "宣傳組",
    "職稱-華語": "組員",
    "職稱-en": "Member",
    "最後更新時間": "2020-11-30T07:34:12.000Z"
  },
  {
    "_id": "recSwD2lYqmFOQcTM",
    "id": "recSwD2lYqmFOQcTM",
    "顯示名稱-華語": "子魚",
    "顯示名稱-en": "Lisa Lin",
    "大頭照": "cache/2309ac08e57d10e2b0ea2550e6833ce5.jpg",
    "組別": "議程委員會",
    "職稱-華語": "議程委員",
    "職稱-en": "Member",
    "最後更新時間": "2020-11-30T07:34:13.000Z"
  },
  {
    "_id": "recgrSgeafVZrvW1g",
    "id": "recgrSgeafVZrvW1g",
    "顯示名稱-華語": "筱翎 sherry",
    "顯示名稱-en": "Hsiaoling (sherry) ",
    "大頭照": "cache/e74b4b92ec20e40206c0a6edff02cd8d.jpg",
    "組別": "總籌組",
    "職稱-華語": "執行秘書",
    "職稱-en": "Executive Secretary",
    "最後更新時間": "2020-11-30T02:35:11.000Z"
  },
  {
    "_id": "recALz1FVYW94IRfo",
    "id": "recALz1FVYW94IRfo",
    "顯示名稱-華語": "Bess Lee",
    "顯示名稱-en": "Bess Lee",
    "大頭照": "cache/150f56d02ecdd7f00b59a592b46c01a3.png",
    "組別": "總籌組",
    "職稱-華語": "共同召集人",
    "職稱-en": "Co-chair",
    "是頭頭": true,
    "最後更新時間": "2020-11-30T07:35:37.000Z"
  },
  {
    "_id": "recVs8wH49Ww0XlrR",
    "id": "recVs8wH49Ww0XlrR",
    "顯示名稱-華語": "Isabel Hou",
    "顯示名稱-en": "Isabel Hou",
    "大頭照": "cache/bf6d5ce83b5c784d51a3f2d06ee17ae9.jpg",
    "組別": "總籌組",
    "職稱-華語": "共同主辦 - g0v 零時政府揪松團",
    "職稱-en": "Co-host: g0v jothon",
    "最後更新時間": "2020-11-30T07:35:36.000Z"
  },
  {
    "_id": "recHPMdEFY2t7m0yT",
    "id": "recHPMdEFY2t7m0yT",
    "顯示名稱-華語": "皮皮",
    "顯示名稱-en": "pipi",
    "大頭照": "cache/5ac1792fea2d7ab257928b30696f9378.jpg",
    "組別": "議程組",
    "職稱-華語": "組員",
    "職稱-en": "Member",
    "最後更新時間": "2020-11-30T07:34:18.000Z"
  },
  {
    "_id": "rec7ebWTEfv587Oh0",
    "id": "rec7ebWTEfv587Oh0",
    "顯示名稱-華語": "皇甫",
    "顯示名稱-en": "HuangFu",
    "組別": "總籌組",
    "職稱-華語": "組員",
    "Gravatar 信箱": "8736be8c51ac811dcb13b7297274a8fb",
    "職稱-en": "Member",
    "最後更新時間": "2020-11-30T07:34:20.000Z"
  },
  {
    "_id": "rec5yOeLFISr9m7yh",
    "id": "rec5yOeLFISr9m7yh",
    "顯示名稱-華語": "皇甫",
    "顯示名稱-en": "HuangFu",
    "組別": "財務組",
    "職稱-華語": "組長",
    "Gravatar 信箱": "8736be8c51ac811dcb13b7297274a8fb",
    "職稱-en": "Head",
    "是頭頭": true,
    "最後更新時間": "2020-11-30T10:32:44.000Z"
  },
  {
    "_id": "recTV4L6CfisZCfS0",
    "id": "recTV4L6CfisZCfS0",
    "顯示名稱-華語": "雁雁",
    "顯示名稱-en": "Ian Liu",
    "大頭照": "cache/0942283c5a7a794ded435362e55ce1ab.jpg",
    "組別": "財務組",
    "職稱-華語": "出納",
    "Gravatar 信箱": "5712c31d5c288ea6159f18257b164d2f",
    "職稱-en": "Cashier",
    "最後更新時間": "2020-11-30T02:34:54.000Z"
  },
  {
    "_id": "rec6sSpbT01czznjD",
    "id": "rec6sSpbT01czznjD",
    "顯示名稱-華語": "chihao",
    "顯示名稱-en": "chihao",
    "大頭照": "cache/40ee94aac8085c9c2269c6b40ee6f54e.jpg",
    "組別": "總籌組",
    "職稱-華語": "共同召集人",
    "職稱-en": "Co-chair",
    "是頭頭": true,
    "最後更新時間": "2020-11-30T07:36:05.000Z"
  },
  {
    "_id": "recwwlPBvIsvSZVoR",
    "id": "recwwlPBvIsvSZVoR",
    "顯示名稱-華語": "立弘",
    "顯示名稱-en": "RockLeon ",
    "大頭照": "cache/66556157d4f424fa5c31b76d1eb177db.jpg",
    "組別": "宣傳組",
    "職稱-華語": "設計師",
    "職稱-en": "Designer",
    "最後更新時間": "2020-11-30T02:34:36.000Z"
  },
  {
    "_id": "recoT9ionW2slRjo0",
    "id": "recoT9ionW2slRjo0",
    "顯示名稱-華語": "史丹馬",
    "顯示名稱-en": "Stan",
    "大頭照": "cache/d293b226b6de96a3e9e37f5b627292bd.jpg",
    "組別": "場務組",
    "職稱-華語": "組員",
    "職稱-en": "Member",
    "最後更新時間": "2020-11-30T07:34:26.000Z"
  },
  {
    "_id": "recDouVkgVKeQ6Tkg",
    "id": "recDouVkgVKeQ6Tkg",
    "顯示名稱-華語": "Bobby",
    "顯示名稱-en": "Bobby",
    "大頭照": "cache/a10f27fa4fd186eb221f84fb6384986e.jpg",
    "組別": "議程組",
    "職稱-華語": "組員",
    "職稱-en": "Member",
    "最後更新時間": "2020-11-30T07:34:28.000Z"
  },
  {
    "_id": "reco3FWgL6MUh1ZYs",
    "id": "reco3FWgL6MUh1ZYs",
    "顯示名稱-華語": "Can",
    "顯示名稱-en": "Can",
    "組別": "直播組",
    "職稱-華語": "組員",
    "Gravatar 信箱": "f6e117aa49266ba60fabf42c195f00de",
    "職稱-en": "Member",
    "最後更新時間": "2020-11-30T07:34:28.000Z"
  },
  {
    "_id": "recStETQ1tR4uIthn",
    "id": "recStETQ1tR4uIthn",
    "顯示名稱-華語": "eva",
    "顯示名稱-en": "eva",
    "大頭照": "cache/7ba9f3493e72164c922dd2c5e0734f91.png",
    "組別": "直播組",
    "職稱-華語": "組員",
    "職稱-en": "Member",
    "最後更新時間": "2020-11-30T07:34:28.000Z"
  },
  {
    "_id": "recT0EQF4b1MuL1Sb",
    "id": "recT0EQF4b1MuL1Sb",
    "顯示名稱-華語": "雨停",
    "顯示名稱-en": "YuTin",
    "大頭照": "cache/f3f88e4b708d5cb5a217c05325614375.jpg",
    "組別": "直播組",
    "職稱-華語": "組長",
    "職稱-en": "Head",
    "是頭頭": true,
    "最後更新時間": "2020-11-30T02:39:23.000Z"
  },
  {
    "_id": "recjFTjF5ggyY0n3V",
    "id": "recjFTjF5ggyY0n3V",
    "顯示名稱-華語": "山葵泥",
    "大頭照": "cache/d7d26fbb805ffef0a340129e9c242000.jpg",
    "組別": "直播組",
    "職稱-華語": "組員",
    "職稱-en": "Member",
    "最後更新時間": "2020-11-30T07:34:30.000Z"
  },
  {
    "_id": "recFd99uEdds9Xmwb",
    "id": "recFd99uEdds9Xmwb",
    "顯示名稱-華語": "王世勲",
    "大頭照": "cache/aaa4a532377696bc61bec2f6138a72a4.jpg",
    "組別": "紀錄組",
    "職稱-華語": "組員",
    "職稱-en": "Member",
    "最後更新時間": "2020-11-30T07:34:30.000Z"
  },
  {
    "_id": "rec0fAeAuXoqEfeXf",
    "id": "rec0fAeAuXoqEfeXf",
    "顯示名稱-華語": "Erin",
    "顯示名稱-en": "Erin",
    "大頭照": "cache/e3926202c606d1f88126682f85ed7812.jpg",
    "組別": "紀錄組",
    "職稱-華語": "組長",
    "職稱-en": "Head",
    "是頭頭": true,
    "最後更新時間": "2020-11-30T02:39:20.000Z"
  },
  {
    "_id": "recHDQdsJzuzIYZjd",
    "id": "recHDQdsJzuzIYZjd",
    "顯示名稱-華語": "Ijs",
    "顯示名稱-en": "Ijs",
    "大頭照": "cache/f40ef9ed4399cdf683df1b71437b8d43.jpg",
    "組別": "宣傳組",
    "職稱-華語": "用嘴出設計那個",
    "Gravatar 信箱": "8dae6a578844de853c10e338e829c486",
    "職稱-en": "Head",
    "是頭頭": true,
    "最後更新時間": "2020-11-30T02:39:25.000Z"
  },
  {
    "_id": "recag2PIf5szw6Uw5",
    "id": "recag2PIf5szw6Uw5",
    "顯示名稱-華語": "Lia",
    "顯示名稱-en": "Lia",
    "大頭照": "cache/7b54ece307938dceafcc046ff0ca88e4.jpg",
    "組別": "宣傳組",
    "職稱-華語": "設計師",
    "職稱-en": "Designer",
    "最後更新時間": "2020-11-30T02:34:38.000Z"
  },
  {
    "_id": "recNX6Hz7mZIVcvfJ",
    "id": "recNX6Hz7mZIVcvfJ",
    "顯示名稱-華語": "Ivc",
    "顯示名稱-en": "Ivc",
    "組別": "宣傳組",
    "職稱-華語": "設計師",
    "職稱-en": "Designer",
    "最後更新時間": "2020-11-30T02:34:38.000Z"
  },
  {
    "_id": "recOUI10QlgGG9G5a",
    "id": "recOUI10QlgGG9G5a",
    "顯示名稱-華語": "Ijs",
    "顯示名稱-en": "Ijs",
    "大頭照": "cache/daf86ab1f0792940a6b0ec3c3db0bea8.jpg",
    "組別": "場務組",
    "職稱-華語": "嘴砲組員",
    "Gravatar 信箱": "8dae6a578844de853c10e338e829c486",
    "職稱-en": "Member",
    "最後更新時間": "2020-11-30T07:34:35.000Z"
  },
  {
    "_id": "recX43my0GbCK1vvg",
    "id": "recX43my0GbCK1vvg",
    "顯示名稱-華語": "stella",
    "顯示名稱-en": "stella",
    "大頭照": "cache/7e1a6f1c573718717797d7b7a433a1df.jpg",
    "組別": "直播組",
    "職稱-華語": "組員",
    "職稱-en": "Member",
    "最後更新時間": "2020-11-30T07:34:36.000Z"
  },
  {
    "_id": "recSbGmXlCYR84UTM",
    "id": "recSbGmXlCYR84UTM",
    "顯示名稱-華語": "stella",
    "顯示名稱-en": "stella",
    "大頭照": "cache/d75319121ecd031bb3ab7fa717044c37.jpg",
    "組別": "宣傳組",
    "職稱-華語": "設計師",
    "職稱-en": "Designer",
    "最後更新時間": "2020-11-30T02:34:38.000Z"
  },
  {
    "_id": "recgvlQ7cCd0tsGr1",
    "id": "recgvlQ7cCd0tsGr1",
    "顯示名稱-華語": "YI-YAN",
    "顯示名稱-en": "YI-YAN",
    "大頭照": "cache/f3155a26aa59aaad0b45c05f25029105.jpg",
    "組別": "場務組",
    "職稱-華語": "組員",
    "職稱-en": "Member",
    "最後更新時間": "2020-11-30T07:34:38.000Z"
  },
  {
    "_id": "recRMG60Dm7a9iJZe",
    "id": "recRMG60Dm7a9iJZe",
    "顯示名稱-華語": "哲輔 @hkazami",
    "顯示名稱-en": "Steven @hkazami",
    "大頭照": "cache/5a723fce28e6116671856646f9b5f45d.jpg",
    "組別": "議程組",
    "職稱-華語": "組長",
    "職稱-en": "Head",
    "是頭頭": true,
    "最後更新時間": "2020-11-30T02:39:30.000Z"
  },
  {
    "_id": "recqUVccxpIYEnJ8R",
    "id": "recqUVccxpIYEnJ8R",
    "顯示名稱-華語": "熊",
    "顯示名稱-en": "hsiang",
    "大頭照": "cache/ed73a533501191caf0669f98fe2c56f8.jpg",
    "組別": "總籌組",
    "職稱-華語": "共同主辦 - 南方創客基地",
    "職稱-en": "Co-host: Fablab Tainan",
    "最後更新時間": "2020-11-30T07:35:33.000Z"
  },
  {
    "_id": "recfwEF3JcCE0uQan",
    "id": "recfwEF3JcCE0uQan",
    "顯示名稱-華語": "淨文",
    "顯示名稱-en": "Jingwen",
    "大頭照": "cache/2d894c4bf78dc51d6013733d6f78a3b1.png",
    "組別": "場務組",
    "職稱-華語": "組長",
    "職稱-en": "Head",
    "是頭頭": true,
    "最後更新時間": "2020-11-30T02:39:13.000Z"
  },
  {
    "_id": "recFQtY4WUhYE03Rs",
    "id": "recFQtY4WUhYE03Rs",
    "顯示名稱-華語": "聆",
    "顯示名稱-en": "Ling",
    "大頭照": "cache/45e909a7886b26025602cb92aee811b9.jpg",
    "組別": "場務組",
    "職稱-華語": "組員",
    "職稱-en": "Member",
    "最後更新時間": "2020-11-30T07:34:42.000Z"
  },
  {
    "_id": "reccPq8jQN9VTHn9t",
    "id": "reccPq8jQN9VTHn9t",
    "顯示名稱-華語": "STeven26",
    "顯示名稱-en": "STeven26",
    "大頭照": "cache/cb7d0c36c99bbe5867a7ad36cf6d89dc.jpg",
    "組別": "宣傳組",
    "職稱-華語": "設計師",
    "職稱-en": "Designer",
    "最後更新時間": "2020-11-30T02:34:38.000Z"
  },
  {
    "_id": "recZ2RoXu4EvcUNCH",
    "id": "recZ2RoXu4EvcUNCH",
    "顯示名稱-華語": "Ping",
    "顯示名稱-en": "Ping",
    "組別": "紀錄組",
    "職稱-華語": "組員",
    "職稱-en": "Member",
    "最後更新時間": "2020-11-30T07:34:44.000Z"
  },
  {
    "_id": "reciZtLRtuZp16Z0V",
    "id": "reciZtLRtuZp16Z0V",
    "顯示名稱-華語": "阿谷",
    "顯示名稱-en": "Thompson",
    "大頭照": "cache/be86ff7ba4c9c3afd255f2e822defab5.jpg",
    "組別": "場務組",
    "職稱-華語": "組員",
    "職稱-en": "Member",
    "最後更新時間": "2020-11-30T07:34:47.000Z"
  },
  {
    "_id": "recSKob1nV1yTLxfB",
    "id": "recSKob1nV1yTLxfB",
    "顯示名稱-華語": "wiasliaw",
    "顯示名稱-en": "wiasliaw",
    "組別": "場務組",
    "職稱-華語": "組員",
    "Gravatar 信箱": "9c4fb425d099a2ce2f0f163e0df71f1a",
    "職稱-en": "Member",
    "最後更新時間": "2020-11-30T07:34:47.000Z"
  },
  {
    "_id": "recuLHkNDewWAVG68",
    "id": "recuLHkNDewWAVG68",
    "顯示名稱-華語": "家康",
    "組別": "紀錄組",
    "職稱-華語": "組員",
    "職稱-en": "Member",
    "最後更新時間": "2020-11-30T07:34:47.000Z"
  },
  {
    "_id": "recewqjz1GswCbRw5",
    "id": "recewqjz1GswCbRw5",
    "顯示名稱-華語": "芒果蘇",
    "顯示名稱-en": "mangoSu",
    "大頭照": "cache/8b973d59f5f8020c3ef2ff39c5b23dee.png",
    "組別": "宣傳組",
    "職稱-華語": "組員",
    "職稱-en": "Member",
    "最後更新時間": "2020-12-05T16:33:22.000Z"
  },
  {
    "_id": "recmJ5DNalKPnKQ3I",
    "id": "recmJ5DNalKPnKQ3I",
    "顯示名稱-華語": "夢瑤",
    "顯示名稱-en": "Mavis",
    "大頭照": "cache/95f50685fbbc9d834633eaeab90845b2.jpg",
    "組別": "場務組",
    "職稱-華語": "組長",
    "職稱-en": "Head",
    "是頭頭": true,
    "最後更新時間": "2020-11-30T02:39:13.000Z"
  },
  {
    "_id": "recWSeCVo3h6MPRDK",
    "id": "recWSeCVo3h6MPRDK",
    "顯示名稱-華語": "楊麗蓉",
    "顯示名稱-en": "Minnie Yang",
    "大頭照": "cache/57949b46dbb61ef9ba15e4684a60be41.jpg",
    "組別": "場務組",
    "職稱-華語": "組員",
    "職稱-en": "Member",
    "最後更新時間": "2020-11-30T07:34:50.000Z"
  },
  {
    "_id": "recVNO5MFLLX15c9N",
    "id": "recVNO5MFLLX15c9N",
    "顯示名稱-華語": "Howard",
    "顯示名稱-en": "Howard",
    "大頭照": "cache/98971d0f3fd43650f88f68ca1bc4a9de.jpg",
    "組別": "總籌組",
    "職稱-華語": "共同主辦 - 好想工作室",
    "職稱-en": "Co-host: Goodideas-Studio",
    "最後更新時間": "2020-11-30T07:35:27.000Z"
  },
  {
    "_id": "recATJKIktanMate9",
    "id": "recATJKIktanMate9",
    "顯示名稱-華語": "Swim",
    "顯示名稱-en": "Swim",
    "組別": "宣傳組",
    "職稱-華語": "組員",
    "職稱-en": "Member",
    "最後更新時間": "2020-11-30T07:34:53.000Z"
  },
  {
    "_id": "recZEbYSmbNrICB14",
    "id": "recZEbYSmbNrICB14",
    "顯示名稱-華語": "Lai",
    "顯示名稱-en": "Lai",
    "大頭照": "cache/5dc3bbb274c54056aa97256ce6d29749.jpg",
    "組別": "宣傳組",
    "職稱-華語": "組員",
    "職稱-en": "Member",
    "最後更新時間": "2020-12-05T16:33:27.000Z"
  },
  {
    "_id": "recoXunDTZBB7gEKj",
    "id": "recoXunDTZBB7gEKj",
    "顯示名稱-華語": "林宸亦",
    "顯示名稱-en": "James",
    "大頭照": "cache/f394bd6cd88e12e28ebb8c4d0cb09d41.jpg",
    "組別": "紀錄組",
    "職稱-華語": "組員",
    "Gravatar 信箱": "a18f49307d456473582d85915abd337a",
    "職稱-en": "Member",
    "最後更新時間": "2020-11-30T07:34:54.000Z"
  },
  {
    "_id": "recyojqM8p5FIo8QV",
    "id": "recyojqM8p5FIo8QV",
    "顯示名稱-華語": "游諭",
    "顯示名稱-en": "Tsungyu",
    "組別": "紀錄組",
    "職稱-華語": "組員",
    "職稱-en": "Member",
    "最後更新時間": "2020-11-30T07:34:56.000Z"
  },
  {
    "_id": "reccLaEWdRUR2qk6Z",
    "id": "reccLaEWdRUR2qk6Z",
    "顯示名稱-華語": "傅威翔",
    "顯示名稱-en": "WEI-SIANG FU",
    "大頭照": "cache/ab73ed6a6330d0d4423da332e400aba1.jpg",
    "組別": "紀錄組",
    "職稱-華語": "組員",
    "職稱-en": "Member",
    "最後更新時間": "2020-11-30T07:34:56.000Z"
  },
  {
    "_id": "recNHIXCkbpuxKBvQ",
    "id": "recNHIXCkbpuxKBvQ",
    "顯示名稱-華語": "俗於",
    "顯示名稱-en": "SHU YU",
    "大頭照": "cache/bceef1b1f74c7ed745171d10f1b19368.jpg",
    "組別": "場務組",
    "職稱-華語": "組員",
    "職稱-en": "Member",
    "最後更新時間": "2020-11-30T07:34:56.000Z"
  },
  {
    "_id": "recugm9aZm5bwVOdB",
    "id": "recugm9aZm5bwVOdB",
    "顯示名稱-華語": "大元",
    "顯示名稱-en": "DaYuan",
    "大頭照": "cache/edccf618c7cd7db3377203fcae00f9f8.png",
    "組別": "場務組",
    "職稱-華語": "組員",
    "職稱-en": "Member",
    "最後更新時間": "2020-11-30T07:34:56.000Z"
  },
  {
    "_id": "recjc1YohomuI4kRC",
    "id": "recjc1YohomuI4kRC",
    "顯示名稱-華語": "林柏呈",
    "顯示名稱-en": "Jerry Lin",
    "大頭照": "cache/4189e4164f4aa3ecc17cf74dc0b8fc67.jpg",
    "組別": "場務組",
    "職稱-華語": "組員",
    "職稱-en": "Member",
    "最後更新時間": "2020-11-30T07:34:56.000Z"
  },
  {
    "_id": "recOmOBVOrFzsTKQh",
    "id": "recOmOBVOrFzsTKQh",
    "顯示名稱-華語": "嘉華",
    "顯示名稱-en": "Chia-Hua",
    "組別": "場務組",
    "職稱-華語": "組員",
    "職稱-en": "Member",
    "最後更新時間": "2020-11-30T07:34:56.000Z"
  },
  {
    "_id": "recqojGpohhgRlJxX",
    "id": "recqojGpohhgRlJxX",
    "顯示名稱-華語": "余巧玉",
    "顯示名稱-en": "Chiaoyu yu",
    "大頭照": "cache/537d6c2d27b0c5f940e306be4d38702e.jpg",
    "組別": "場務組",
    "職稱-華語": "組員",
    "職稱-en": "Member",
    "最後更新時間": "2020-11-30T07:34:56.000Z"
  },
  {
    "_id": "rechPtOVcdGtVEVFy",
    "id": "rechPtOVcdGtVEVFy",
    "顯示名稱-華語": "珊珊",
    "顯示名稱-en": "Shanshan",
    "大頭照": "cache/b631dc814b3a044ae489729234d47f04.jpg",
    "組別": "場務組",
    "職稱-華語": "組員",
    "職稱-en": "Member",
    "最後更新時間": "2020-11-30T07:34:56.000Z"
  },
  {
    "_id": "rec3KjESpJMZ7DoZp",
    "id": "rec3KjESpJMZ7DoZp",
    "顯示名稱-華語": "WILT CHEN",
    "顯示名稱-en": "WILT CHEN",
    "大頭照": "cache/749bf160214dcb1029cf5558163d194c.jpg",
    "組別": "口譯組",
    "職稱-華語": "組長",
    "職稱-en": "Head",
    "是頭頭": true,
    "最後更新時間": "2020-11-30T02:39:18.000Z"
  },
  {
    "_id": "recIsEVma7xkfdNeB",
    "id": "recIsEVma7xkfdNeB",
    "顯示名稱-華語": "五十元",
    "顯示名稱-en": "50yent",
    "大頭照": "cache/a0cf9a95d109644394a789bdf1ec873e.jpg",
    "組別": "場務組",
    "職稱-華語": "組長",
    "職稱-en": "Head",
    "是頭頭": true,
    "最後更新時間": "2020-11-30T02:39:14.000Z"
  },
  {
    "_id": "recQOTriOgKZTdNSK",
    "id": "recQOTriOgKZTdNSK",
    "顯示名稱-華語": "許蘇菲",
    "顯示名稱-en": "Sophie",
    "大頭照": "cache/2e883cefb28f60f4887f71c2aca9a991.jpg",
    "組別": "場務組",
    "職稱-華語": "組員",
    "職稱-en": "Member",
    "最後更新時間": "2020-11-30T07:35:00.000Z"
  },
  {
    "_id": "recNp93fM4GP6HAXa",
    "id": "recNp93fM4GP6HAXa",
    "顯示名稱-華語": "高安潔",
    "顯示名稱-en": "Angela Kao",
    "大頭照": "cache/797625b39cf2995eb3fd7fade28f0bd2.jpg",
    "組別": "口譯組",
    "職稱-華語": "組員",
    "職稱-en": "Member",
    "最後更新時間": "2020-11-30T07:35:02.000Z"
  },
  {
    "_id": "recUOTi21cGsrrM8T",
    "id": "recUOTi21cGsrrM8T",
    "顯示名稱-華語": "QQ",
    "顯示名稱-en": "QQ",
    "大頭照": "cache/fbdbc64d2bda1c417bd5da9db76c44f9.jpg",
    "組別": "口譯組",
    "職稱-華語": "組員",
    "職稱-en": "Member",
    "最後更新時間": "2020-11-30T07:35:02.000Z"
  },
  {
    "_id": "recBCodx2AokLHRpu",
    "id": "recBCodx2AokLHRpu",
    "顯示名稱-華語": "NN",
    "顯示名稱-en": "NN",
    "大頭照": "cache/248a54addc8797054f1c4374d562ab5a.jpg",
    "組別": "口譯組",
    "職稱-華語": "組員",
    "職稱-en": "Member",
    "最後更新時間": "2020-11-30T07:35:02.000Z"
  },
  {
    "_id": "rectRx7gMYpGRLmUU",
    "id": "rectRx7gMYpGRLmUU",
    "顯示名稱-華語": "卡洛",
    "顯示名稱-en": "Caro ",
    "大頭照": "cache/cdb982edab1ac007a01faa22c30ad3a5.jpg",
    "組別": "口譯組",
    "職稱-華語": "組員",
    "職稱-en": "Member",
    "最後更新時間": "2020-11-30T07:35:02.000Z"
  },
  {
    "_id": "recyWUI7aOyYLxg4X",
    "id": "recyWUI7aOyYLxg4X",
    "顯示名稱-華語": "盧昱廷",
    "組別": "紀錄組",
    "職稱-華語": "組員",
    "職稱-en": "Member",
    "最後更新時間": "2020-11-30T07:35:02.000Z"
  },
  {
    "_id": "rec3yAV0WkOkJenHt",
    "id": "rec3yAV0WkOkJenHt",
    "顯示名稱-華語": "小 P",
    "組別": "紀錄組",
    "職稱-華語": "組員",
    "職稱-en": "Member",
    "最後更新時間": "2020-11-30T07:35:02.000Z"
  },
  {
    "_id": "reczILAvEEYVHjPdf",
    "id": "reczILAvEEYVHjPdf",
    "顯示名稱-華語": "威宏",
    "顯示名稱-en": "Wei",
    "大頭照": "cache/ad3a0d5bcd5c805a94bfd79e4315960b.jpg",
    "組別": "紀錄組",
    "職稱-華語": "組員",
    "職稱-en": "Member",
    "最後更新時間": "2020-11-30T07:35:02.000Z"
  },
  {
    "_id": "rechufsd7CC1mxrZQ",
    "id": "rechufsd7CC1mxrZQ",
    "顯示名稱-華語": "嚴婉玲",
    "顯示名稱-en": "Urda Yen",
    "組別": "宣傳組",
    "職稱-華語": "組長",
    "職稱-en": "Head",
    "是頭頭": true,
    "最後更新時間": "2020-11-30T07:36:52.000Z"
  },
  {
    "_id": "recIVjItSslLgDCK5",
    "id": "recIVjItSslLgDCK5",
    "顯示名稱-華語": "Scott",
    "顯示名稱-en": "Scott",
    "組別": "議程組",
    "職稱-華語": "組員",
    "Gravatar 信箱": "383ba4dca5fdc4de2b4f3f157ad085e8",
    "職稱-en": "Member",
    "最後更新時間": "2020-11-30T07:35:02.000Z"
  },
  {
    "_id": "recO7KOg9ogzbLQXC",
    "id": "recO7KOg9ogzbLQXC",
    "顯示名稱-華語": "Pomin Wu",
    "顯示名稱-en": "Pomin Wu",
    "大頭照": "cache/2d4fef9e3a4b8ac46afabe6aaa27e07c.jpg",
    "組別": "總籌組",
    "職稱-華語": "共同召集人",
    "職稱-en": "Co-Chair",
    "是頭頭": true,
    "最後更新時間": "2020-11-30T02:39:35.000Z"
  },
  {
    "_id": "recXuBpMvSN77h2Nt",
    "id": "recXuBpMvSN77h2Nt",
    "顯示名稱-華語": "Oliver",
    "顯示名稱-en": "Oliver",
    "大頭照": "cache/766c532564144cccc4a5e38d567ba828.jpg",
    "組別": "議程組",
    "職稱-華語": "組員",
    "職稱-en": "Member",
    "最後更新時間": "2020-11-30T07:35:07.000Z"
  },
  {
    "_id": "recmYB82MnAP40GIl",
    "id": "recmYB82MnAP40GIl",
    "顯示名稱-華語": "Emily Lu",
    "顯示名稱-en": "Emily Lu",
    "大頭照": "cache/d0d97c3f5fc00f948861856264e862d2.png",
    "組別": "場務組",
    "職稱-華語": "組員",
    "職稱-en": "Member",
    "最後更新時間": "2020-11-30T07:35:08.000Z"
  },
  {
    "_id": "recFeKX6XksNAfTrO",
    "id": "recFeKX6XksNAfTrO",
    "顯示名稱-華語": "Claire",
    "顯示名稱-en": "Claire",
    "組別": "議程組",
    "職稱-華語": "組員",
    "職稱-en": "Member",
    "最後更新時間": "2020-11-30T07:35:09.000Z"
  },
  {
    "_id": "rec2xe3vzhw2yVkYV",
    "id": "rec2xe3vzhw2yVkYV",
    "顯示名稱-華語": "Keira 亭君",
    "顯示名稱-en": "Keira",
    "組別": "場務組",
    "職稱-華語": "組長",
    "職稱-en": "Head",
    "是頭頭": true,
    "最後更新時間": "2020-11-30T02:39:12.000Z"
  },
  {
    "_id": "reck98uEpdFMnhJsl",
    "id": "reck98uEpdFMnhJsl",
    "顯示名稱-華語": "八六",
    "顯示名稱-en": "Ian Hung (86)",
    "大頭照": "cache/aa2f5cf28468e79f7edb0f3b74132fc2.jpg",
    "組別": "議程組",
    "職稱-華語": "組員",
    "職稱-en": "Member",
    "最後更新時間": "2020-11-30T07:35:09.000Z"
  },
  {
    "_id": "recqgSl8ZwYbtj0zJ",
    "id": "recqgSl8ZwYbtj0zJ",
    "顯示名稱-華語": "宏宏",
    "顯示名稱-en": "Aidan",
    "組別": "議程組",
    "職稱-華語": "組員",
    "Gravatar 信箱": "27d0bfb6c35e170579b528c9bcf002b0",
    "職稱-en": "Member",
    "最後更新時間": "2020-11-30T07:35:10.000Z"
  },
  {
    "_id": "recd9JWdsHauVoRBM",
    "id": "recd9JWdsHauVoRBM",
    "顯示名稱-華語": "嚴婉玲",
    "顯示名稱-en": "Urda Yen",
    "組別": "總籌組",
    "職稱-華語": "共同主辦 - 台南新芽",
    "職稱-en": "Co-host: Tainan Sprout",
    "最後更新時間": "2020-11-30T07:35:16.000Z"
  },
  {
    "_id": "rec5EEv01TYSbvVpb",
    "id": "rec5EEv01TYSbvVpb",
    "顯示名稱-華語": "Mouse Kuo",
    "顯示名稱-en": "Mouse Kuo",
    "組別": "設備組",
    "職稱-華語": "組長  (from KlickKlack)",
    "職稱-en": "Head (from KlickKlack)",
    "是頭頭": true,
    "最後更新時間": "2020-11-30T04:42:27.000Z"
  },
  {
    "_id": "recAu90dVg6sD3ijC",
    "id": "recAu90dVg6sD3ijC",
    "顯示名稱-華語": "Debby Lu",
    "顯示名稱-en": "Debby Lu",
    "組別": "設備組",
    "職稱-華語": "組員 (from KlickKlack)",
    "職稱-en": "Staff (from KlickKlack)",
    "最後更新時間": "2020-11-30T04:42:34.000Z"
  },
  {
    "_id": "recxoGbyTsRLFt79L",
    "id": "recxoGbyTsRLFt79L",
    "顯示名稱-華語": "Jerry Chen",
    "顯示名稱-en": "Jerry Chen",
    "組別": "設備組",
    "職稱-華語": "組員 (from KlickKlack)",
    "職稱-en": "Staff (from KlickKlack)",
    "最後更新時間": "2020-11-30T07:38:42.000Z"
  },
  {
    "_id": "reclRe5BBmUMAYWqj",
    "id": "reclRe5BBmUMAYWqj",
    "顯示名稱-華語": "Muka",
    "顯示名稱-en": "Muka",
    "組別": "設備組",
    "職稱-華語": "組員 (from Micare)",
    "職稱-en": "Staff (from Micare)",
    "最後更新時間": "2020-11-30T02:30:36.000Z"
  },
  {
    "_id": "recku9FkkEqeoGhtY",
    "id": "recku9FkkEqeoGhtY",
    "顯示名稱-華語": "Daisuke",
    "顯示名稱-en": "Daisuke",
    "組別": "設備組",
    "職稱-華語": "組員 (from Micare)",
    "職稱-en": "Staff (from Micare)",
    "最後更新時間": "2020-11-30T02:30:42.000Z"
  },
  {
    "_id": "recBqJS7wi1OoKO4u",
    "id": "recBqJS7wi1OoKO4u",
    "顯示名稱-華語": "Cjoker",
    "顯示名稱-en": "Cjoker",
    "組別": "設備組",
    "職稱-華語": "組員 (from Micare)",
    "職稱-en": "Staff (from Micare)",
    "最後更新時間": "2020-11-30T02:30:28.000Z"
  },
  {
    "_id": "recaKEhaBbSl5h2GL",
    "id": "recaKEhaBbSl5h2GL",
    "顯示名稱-華語": "YYH",
    "顯示名稱-en": "YYH",
    "組別": "票務組",
    "職稱-華語": "組長",
    "職稱-en": "Head",
    "是頭頭": true,
    "最後更新時間": "2020-11-30T02:39:27.000Z"
  },
  {
    "_id": "recoepLgl0ojalzkW",
    "id": "recoepLgl0ojalzkW",
    "顯示名稱-華語": "劉致昕",
    "顯示名稱-en": "Jason Liu",
    "大頭照": "cache/d7578eb9a40a1a1dec7371067f529921.jpg",
    "組別": "議程委員會",
    "職稱-華語": "議程委員",
    "職稱-en": "Member",
    "最後更新時間": "2020-11-30T07:33:55.000Z"
  },
  {
    "_id": "reclRDjyhzsXKwRFw",
    "id": "reclRDjyhzsXKwRFw",
    "顯示名稱-華語": "ly",
    "顯示名稱-en": "ly",
    "大頭照": "cache/77c1f43c9d4073ef20a5db7b16b08020.jpg",
    "組別": "議程委員會",
    "職稱-華語": "議程委員",
    "職稱-en": "Member",
    "最後更新時間": "2020-11-30T07:33:55.000Z"
  },
  {
    "_id": "recO0JK2QmH4CM0k1",
    "id": "recO0JK2QmH4CM0k1",
    "顯示名稱-華語": "Howard Wu",
    "顯示名稱-en": "Howard Wu",
    "大頭照": "cache/1a363aeaf375613e46265f984a57b0e7.jpg",
    "組別": "議程委員會",
    "職稱-華語": "議程委員",
    "職稱-en": "Member",
    "最後更新時間": "2020-11-30T07:33:55.000Z"
  },
  {
    "_id": "recWWUd1hc3oEtduP",
    "id": "recWWUd1hc3oEtduP",
    "顯示名稱-華語": "劉哲瑋",
    "顯示名稱-en": "Chewei",
    "大頭照": "cache/f26ea2f5c955e9209ad4ca18dd7e4019.png",
    "組別": "議程委員會",
    "職稱-華語": "議程委員",
    "職稱-en": "Member",
    "最後更新時間": "2020-11-30T07:33:55.000Z"
  },
  {
    "_id": "reclaY3gAp5ZOyFDq",
    "id": "reclaY3gAp5ZOyFDq",
    "顯示名稱-華語": "ETBlue",
    "顯示名稱-en": "ETBlue",
    "大頭照": "cache/51204da85df5151a9f29cec01d930638.png",
    "組別": "議程委員會",
    "職稱-華語": "議程委員",
    "職稱-en": "Member",
    "最後更新時間": "2020-11-30T07:33:55.000Z"
  },
  {
    "_id": "recShk4BgozPSFizV",
    "id": "recShk4BgozPSFizV",
    "顯示名稱-華語": "張家豪",
    "顯示名稱-en": "Aent",
    "大頭照": "cache/862426fe354a939609e071726e77e38b.png",
    "組別": "議程委員會",
    "職稱-華語": "議程委員",
    "職稱-en": "Member",
    "最後更新時間": "2020-11-30T07:33:55.000Z"
  },
  {
    "_id": "recDe3YbUX1P4yGqz",
    "id": "recDe3YbUX1P4yGqz",
    "顯示名稱-華語": "吳蕙如",
    "顯示名稱-en": "Hueiru",
    "大頭照": "cache/9a28ab30f6050f86d17a215d3f0de9a6.jpg",
    "組別": "議程委員會",
    "職稱-華語": "議程委員",
    "職稱-en": "Member",
    "最後更新時間": "2020-11-30T07:33:54.000Z"
  },
  {
    "_id": "recQq75HhU0C5NeXA",
    "id": "recQq75HhU0C5NeXA",
    "顯示名稱-華語": "RSChiang",
    "顯示名稱-en": "Poren Chiang",
    "大頭照": "cache/146701a56564f05cd5add9412287d88a.png",
    "組別": "宣傳組",
    "最後更新時間": "2020-12-14T15:51:47.000Z"
  }
]